esgvoc/__init__.py
esgvoc/api/__init__.py
esgvoc/api/project_specs.py
esgvoc/api/projects.py
esgvoc/api/py.typed
esgvoc/api/pydantic_handler.py
esgvoc/api/report.py
esgvoc/api/search.py
esgvoc/api/universe.py
esgvoc/api/data_descriptors/__init__.py
esgvoc/api/data_descriptors/activity.py
esgvoc/api/data_descriptors/archive.py
esgvoc/api/data_descriptors/area_label.py
esgvoc/api/data_descriptors/branded_suffix.py
esgvoc/api/data_descriptors/branded_variable.py
esgvoc/api/data_descriptors/citation_url.py
esgvoc/api/data_descriptors/contact.py
esgvoc/api/data_descriptors/conventions.py
esgvoc/api/data_descriptors/creation_date.py
esgvoc/api/data_descriptors/data_descriptor.py
esgvoc/api/data_descriptors/data_specs_version.py
esgvoc/api/data_descriptors/date.py
esgvoc/api/data_descriptors/directory_date.py
esgvoc/api/data_descriptors/drs_specs.py
esgvoc/api/data_descriptors/experiment.py
esgvoc/api/data_descriptors/forcing_index.py
esgvoc/api/data_descriptors/frequency.py
esgvoc/api/data_descriptors/further_info_url.py
esgvoc/api/data_descriptors/grid.py
esgvoc/api/data_descriptors/horizontal_label.py
esgvoc/api/data_descriptors/initialization_index.py
esgvoc/api/data_descriptors/institution.py
esgvoc/api/data_descriptors/known_branded_variable.py
esgvoc/api/data_descriptors/license.py
esgvoc/api/data_descriptors/member_id.py
esgvoc/api/data_descriptors/mip_era.py
esgvoc/api/data_descriptors/model_component.py
esgvoc/api/data_descriptors/nominal_resolution.py
esgvoc/api/data_descriptors/obs_type.py
esgvoc/api/data_descriptors/organisation.py
esgvoc/api/data_descriptors/physics_index.py
esgvoc/api/data_descriptors/product.py
esgvoc/api/data_descriptors/publication_status.py
esgvoc/api/data_descriptors/realization_index.py
esgvoc/api/data_descriptors/realm.py
esgvoc/api/data_descriptors/regex.py
esgvoc/api/data_descriptors/region.py
esgvoc/api/data_descriptors/resolution.py
esgvoc/api/data_descriptors/source.py
esgvoc/api/data_descriptors/source_type.py
esgvoc-2.1.0.dist-info/METADATA
esgvoc-2.1.0.dist-info/WHEEL
esgvoc-2.1.0.dist-info/entry_points.txt
esgvoc-2.1.0.dist-info/licenses/LICENSE.txt
esgvoc-2.1.0.dist-info/RECORD
