Metadata-Version: 2.3
Name: esgvoc
Version: 2.1.0
Summary: python library and CLI to interact with WCRP CVs
Project-URL: Repository, https://github.com/ESGF/esgf-vocab
Author-email: Sébastien Gardoll <sebastien@gardoll.fr>, Guillaume Levavasseur <guillaume.levavasseur@ipsl.fr>, Laurent Troussellier <laurent.troussellier@ipsl.fr>
License: CECILL-2.1
Requires-Python: <3.14,>=3.12
Requires-Dist: idna>=3.10
Requires-Dist: jinja2>=3.1.6
Requires-Dist: platformdirs>=4.3.6
Requires-Dist: pydantic>=2.9.2
Requires-Dist: pyld>=2.0.4
Requires-Dist: pyyaml>=6.0.2
Requires-Dist: requests>=2.32.3
Requires-Dist: sqlalchemy>=2.0.36
Requires-Dist: sqlmodel>=0.0.22
Requires-Dist: toml>=0.10.2
Requires-Dist: typer>=0.15.0
